msgmodel/__init__.py
msgmodel/__main__.py
msgmodel/async_core.py
msgmodel/config.py
msgmodel/core.py
msgmodel/exceptions.py
msgmodel/py.typed
msgmodel/retry.py
msgmodel/security.py
msgmodel/validation.py
msgmodel/providers/__init__.py
msgmodel/providers/anthropic.py
msgmodel/providers/gemini.py
msgmodel/providers/openai.py
msgmodel-4.1.1.dist-info/licenses/LICENSE
msgmodel-4.1.1.dist-info/METADATA
msgmodel-4.1.1.dist-info/WHEEL
msgmodel-4.1.1.dist-info/entry_points.txt
msgmodel-4.1.1.dist-info/top_level.txt
msgmodel-4.1.1.dist-info/RECORD
