Metadata-Version: 2.4
Name: msgmodel
Version: 4.1.1
Summary: Unified Python library for interacting with LLM providers (OpenAI, Gemini, Anthropic Claude). Simple, consistent syntax with stateless design.
Author-email: Leo Dias <lfdias@gmail.com>
Maintainer-email: Leo Dias <lfdias@gmail.com>
License-Expression: MIT
Project-URL: Homepage, https://github.com/LeoooDias/msgModel
Project-URL: Repository, https://github.com/LeoooDias/msgModel
Project-URL: Documentation, https://github.com/LeoooDias/msgModel#readme
Project-URL: Issues, https://github.com/LeoooDias/msgModel/issues
Project-URL: Changelog, https://github.com/LeoooDias/msgModel/releases
Keywords: llm,openai,gemini,anthropic,claude,gpt,ai,machine-learning,chatbot,api,unified,wrapper,async,streaming,retry
Classifier: Development Status :: 4 - Beta
Classifier: Intended Audience :: Developers
Classifier: Operating System :: OS Independent
Classifier: Programming Language :: Python :: 3
Classifier: Programming Language :: Python :: 3.10
Classifier: Programming Language :: Python :: 3.11
Classifier: Programming Language :: Python :: 3.12
Classifier: Programming Language :: Python :: 3.13
Classifier: Topic :: Scientific/Engineering :: Artificial Intelligence
Classifier: Topic :: Software Development :: Libraries :: Python Modules
Classifier: Typing :: Typed
Classifier: Environment :: Console
Classifier: Framework :: AsyncIO
Requires-Python: >=3.10
License-File: LICENSE
Requires-Dist: requests>=2.31.0
Provides-Extra: async
Requires-Dist: aiohttp>=3.9.0; extra == "async"
Provides-Extra: claude
Requires-Dist: anthropic>=0.18.0; extra == "claude"
Provides-Extra: all
Requires-Dist: anthropic>=0.18.0; extra == "all"
Requires-Dist: aiohttp>=3.9.0; extra == "all"
Provides-Extra: dev
Requires-Dist: pytest>=7.0.0; extra == "dev"
Requires-Dist: pytest-cov>=4.0.0; extra == "dev"
Requires-Dist: pytest-asyncio>=0.21.0; extra == "dev"
Requires-Dist: mypy>=1.0.0; extra == "dev"
Requires-Dist: ruff>=0.1.0; extra == "dev"
Requires-Dist: build>=1.0.0; extra == "dev"
Requires-Dist: twine>=4.0.0; extra == "dev"
Requires-Dist: aiohttp>=3.9.0; extra == "dev"
Dynamic: license-file
